{
    "version": "5",
    "minVersion": "5",
    "assets": [
        "assets/prefabs/food/final/caomei_out/caomei.mesh.bin",
        "assets/prefabs/food/final/foodMaterial.mat.json"
    ],
    "entities": [
        {
            "uuid": "0",
            "__class": "@egret/engine/GameEntity",
            "components": [
                {
                    "uuid": "1"
                },
                {
                    "uuid": "2"
                }
            ]
        },
        {
            "uuid": "3",
            "__class": "@egret/engine/GameEntity",
            "components": [
                {
                    "uuid": "4"
                },
                {
                    "uuid": "5"
                },
                {
                    "uuid": "6"
                },
                {
                    "uuid": "58bfa3d7-0567-495a-abf6-813670bd3f12"
                }
            ]
        }
    ],
    "components": [
        {
            "uuid": "1",
            "__class": "@egret/engine/TreeNode",
            "name": "RootNode",
            "children": [
                {
                    "uuid": "4"
                }
            ]
        },
        {
            "uuid": "4",
            "__class": "@egret/engine/TreeNode",
            "name": "caomei"
        },
        {
            "uuid": "5",
            "__class": "@egret/engine/Transform"
        },
        {
            "uuid": "6",
            "__class": "@egret/render/MeshFilter",
            "mesh": {
                "__asset": 0
            }
        },
        {
            "uuid": "58bfa3d7-0567-495a-abf6-813670bd3f12",
            "__class": "@egret/render/MeshRenderer",
            "_nativeLocalBoundingBox": true,
            "_localBoundingBox": [
                -0.377,
                -0.75,
                -0.366,
                0.355,
                -0.14999999999999997,
                0.366
            ],
            "materials": [
                {
                    "__asset": 1
                }
            ]
        },
        {
            "uuid": "2",
            "__class": "@egret/engine/Transform",
            "localRotation": [
                0,
                0,
                0,
                -1
            ]
        }
    ]
}